[
    {
        "id": "1",
        "name": "Cancer Centre"
    }, 
    {
        "id": "2",
        "name": "Collaborative Emergency Centre"
    },
    {
        "id": "3",
        "name": "Foundation"
    },
    {
        "id": "4",
        "name": "Hospital"
    }, 
    {
        "id": "5",
        "name":"Integral Health Facility"
    }, 
    {
        "id": "6",
        "name":"Laboratory"
    },
    {
        "id": "7",
        "name":"Long Term Care Home"
    },
    {
        "id": "8",
        "name":"Mental Health and Addictions Treatment Centre"
    },
    {
        "id": "9",
        "name":"Operational Stress Injury Clinic"
    },
    {
        "id": "10",
        "name":"Operational Stress Injury Clinic"
    },
    {
        "id": "11",
        "name":"Primary Health Care Clinic"
    },
    {
        "id": "12",
        "name":"Public Health Office"
    },
    {
        "id": "13",
        "name":"Surgical Assessment Clinic"
    },
    {
        "id": "14",
        "name":"Urgent Care Centre"
    }
]